target_localjson/__init__.py
target_localjson-0.1.1.dist-info/entry_points.txt
target_localjson-0.1.1.dist-info/WHEEL
target_localjson-0.1.1.dist-info/METADATA
target_localjson-0.1.1.dist-info/RECORD
