Metadata-Version: 2.1
Name: target-localjson
Version: 0.1.1
Summary: A Singer Target for save data to local json files
Author: Wallace Prado
Author-email: wprado@gmail.com
Requires-Python: >=3.8,<4.0
Classifier: Programming Language :: Python :: 3
Classifier: Programming Language :: Python :: 3.8
Classifier: Programming Language :: Python :: 3.9
Requires-Dist: singer-python (>=5.12.1,<6.0.0)
